django_barcode/__init__.py
django_barcode/admin.py
django_barcode/apps.py
django_barcode/core.py
django_barcode/fields.py
django_barcode/models.py
django_barcode/templates/barcode_create.html
django_barcode/templates/barcode_delete.html
django_barcode/templates/barcode_detail.html
django_barcode/templates/barcode_list.html
django_barcode/templates/barcode_update.html
django_barcode/tests.py
django_barcode/urls.py
django_barcode/views.py
django_barcode-0.1.1.dist-info/WHEEL
django_barcode-0.1.1.dist-info/METADATA
django_barcode-0.1.1.dist-info/RECORD
