Metadata-Version: 2.1
Name: django-barcode
Version: 0.1.1
Summary: A simple barcode field for Django models.
Home-page: UNKNOWN
License: UNKNOWN
Author: Andre Guerra
Author-email: andre.catarino.guerra@protonmail.com
Requires-Python: >=3.6,<4.0
Classifier: Programming Language :: Python :: 3
Classifier: Programming Language :: Python :: 3.6
Classifier: Programming Language :: Python :: 3.7
Requires-Dist: django (>=2.1,<3.0)
Requires-Dist: python-barcode (>=0.9.0,<0.10.0)
